PloudosAPI/__init__.py
PloudosAPI/ploudos.py
PloudosAPI-0.1.0.dist-info/METADATA
PloudosAPI-0.1.0.dist-info/WHEEL
PloudosAPI-0.1.0.dist-info/top_level.txt
PloudosAPI-0.1.0.dist-info/RECORD
