Metadata-Version: 2.1
Name: PloudosAPI
Version: 0.1.0
Summary: PloudOS API interactions like starting servers etc.
Author: TimMcCool
Author-email: timmccool.scratch@gmail.com
Keywords: python,ploudos,api,ploudos api,ploudos api wrapper
Classifier: Development Status :: 1 - Planning
Classifier: Intended Audience :: Developers
Classifier: Programming Language :: Python :: 3
Classifier: Operating System :: Unix
Classifier: Operating System :: MacOS :: MacOS X
Classifier: Operating System :: Microsoft :: Windows
Requires-Dist: requests
